sharez/__init__.py
sharez/__main__.py
sharez-0.1.0.dist-info/LICENSE
sharez-0.1.0.dist-info/METADATA
sharez-0.1.0.dist-info/WHEEL
sharez-0.1.0.dist-info/entry_points.txt
sharez-0.1.0.dist-info/top_level.txt
sharez-0.1.0.dist-info/RECORD
