Metadata-Version: 2.1
Name: sharez
Version: 0.1.0
Summary: Share files easily inside your local network
Home-page: https://github.com/mbroton/sharez
Author: Michal Broton
Author-email: michal@broton.dev
Classifier: Programming Language :: Python :: 3
Classifier: Programming Language :: Python :: 3 :: Only
Classifier: Programming Language :: Python :: Implementation :: CPython
Classifier: Programming Language :: Python :: Implementation :: PyPy
Requires-Python: >=3.7
License-File: LICENSE
Requires-Dist: qrcode (==7.3.1)
